{"catalog": [{"id": 1, "chapName": "创造更多的彩虹", "chapUrl": "book62_01.htm"}, {"id": 2, "chapName": "两个佛的会合", "chapUrl": "book62_02.htm"}, {"id": 3, "chapName": "两条河的汇", "chapUrl": "book62_03.htm"}, {"id": 4, "chapName": "你的眼里寄托着世界的希望", "chapUrl": "book62_04.htm"}, {"id": 5, "chapName": "我就是我自己", "chapUrl": "book62_05.htm"}, {"id": 6, "chapName": "我的更名提高了我的境界", "chapUrl": "book62_06.htm"}, {"id": 7, "chapName": "宗师教主（guru）的世界结束了", "chapUrl": "book62_07.htm"}, {"id": 8, "chapName": "真理没有历史", "chapUrl": "book62_08.htm"}, {"id": 9, "chapName": "准备好挨刀", "chapUrl": "book62_09.htm"}, {"id": 10, "chapName": "当我称你为我的朋友，我是真诚的", "chapUrl": "book62_10.htm"}, {"id": 11, "chapName": "唯有创照能展现你的力量", "chapUrl": "book62_11.htm"}, {"id": 12, "chapName": "没有选择，没有抛弃", "chapUrl": "book62_12.htm"}, {"id": 13, "chapName": "附　录", "chapUrl": "book62_13.htm"}], "content": ["无念-永生之花（有关佛陀附体于奥修）", "无念-永生之花", "（有关佛陀附体于奥修）", "No Mind : The Flowers of Eternity", "目录", "："]}